devrev/__init__.py
devrev/client.py
devrev/config.py
devrev/exceptions.py
devrev/py.typed
devrev/models/__init__.py
devrev/models/accounts.py
devrev/models/articles.py
devrev/models/base.py
devrev/models/code_changes.py
devrev/models/conversations.py
devrev/models/dev_users.py
devrev/models/groups.py
devrev/models/links.py
devrev/models/parts.py
devrev/models/rev_users.py
devrev/models/slas.py
devrev/models/tags.py
devrev/models/timeline_entries.py
devrev/models/webhooks.py
devrev/models/works.py
devrev/services/__init__.py
devrev/services/accounts.py
devrev/services/articles.py
devrev/services/base.py
devrev/services/code_changes.py
devrev/services/conversations.py
devrev/services/dev_users.py
devrev/services/groups.py
devrev/services/links.py
devrev/services/parts.py
devrev/services/rev_users.py
devrev/services/slas.py
devrev/services/tags.py
devrev/services/timeline_entries.py
devrev/services/webhooks.py
devrev/services/works.py
devrev/utils/__init__.py
devrev/utils/deprecation.py
devrev/utils/http.py
devrev/utils/logging.py
devrev/utils/pagination.py
devrev_python_sdk-1.0.0.dist-info/METADATA
devrev_python_sdk-1.0.0.dist-info/WHEEL
devrev_python_sdk-1.0.0.dist-info/RECORD
